aidge_export_cpp/__init__.py
aidge_export_cpp/export.py
aidge_export_cpp/export_registry.py
aidge_export_cpp/export_utils.py
aidge_export_cpp/utils.py
aidge_export_cpp/benchmark/registrations/extensions_inference/__init__.py
aidge_export_cpp/benchmark/registrations/extensions_inference/aidge_export_cpp.py
aidge_export_cpp/kernels/abs.hpp
aidge_export_cpp/kernels/activation.hpp
aidge_export_cpp/kernels/batchnorm.hpp
aidge_export_cpp/kernels/concat.hpp
aidge_export_cpp/kernels/convolution.hpp
aidge_export_cpp/kernels/convolution_depthwise.hpp
aidge_export_cpp/kernels/elemwise.hpp
aidge_export_cpp/kernels/erf.hpp
aidge_export_cpp/kernels/fullyconnected.hpp
aidge_export_cpp/kernels/hardmax.hpp
aidge_export_cpp/kernels/identity.hpp
aidge_export_cpp/kernels/leakyrelu.hpp
aidge_export_cpp/kernels/matmul.hpp
aidge_export_cpp/kernels/pad.hpp
aidge_export_cpp/kernels/pooling.hpp
aidge_export_cpp/kernels/reciprocal.hpp
aidge_export_cpp/kernels/reducemean.hpp
aidge_export_cpp/kernels/resize.hpp
aidge_export_cpp/kernels/sigmoid.hpp
aidge_export_cpp/kernels/slice.hpp
aidge_export_cpp/kernels/softmax.hpp
aidge_export_cpp/kernels/sqrt.hpp
aidge_export_cpp/kernels/transpose.hpp
aidge_export_cpp/operators/Abs.py
aidge_export_cpp/operators/BatchNorm.py
aidge_export_cpp/operators/Concat.py
aidge_export_cpp/operators/Conv.py
aidge_export_cpp/operators/ConvDw.py
aidge_export_cpp/operators/ElemWise.py
aidge_export_cpp/operators/Erf.py
aidge_export_cpp/operators/Fc.py
aidge_export_cpp/operators/Hardmax.py
aidge_export_cpp/operators/Identity.py
aidge_export_cpp/operators/MatMul.py
aidge_export_cpp/operators/Pad.py
aidge_export_cpp/operators/Pool.py
aidge_export_cpp/operators/Producer.py
aidge_export_cpp/operators/Quantizer.py
aidge_export_cpp/operators/ReLU.py
aidge_export_cpp/operators/Reciprocal.py
aidge_export_cpp/operators/ReduceMean.py
aidge_export_cpp/operators/Reshape.py
aidge_export_cpp/operators/Resize.py
aidge_export_cpp/operators/Sigmoid.py
aidge_export_cpp/operators/Slice.py
aidge_export_cpp-0.4.1.dist-info/licenses/LICENSE
aidge_export_cpp-0.4.1.dist-info/METADATA
aidge_export_cpp-0.4.1.dist-info/WHEEL
aidge_export_cpp-0.4.1.dist-info/top_level.txt
aidge_export_cpp-0.4.1.dist-info/RECORD
