Metadata-Version: 2.4
Name: aidge_export_cpp
Version: 0.4.1
Summary: Aidge CPP generic export
License: Eclipse Public License - v 2.0
Project-URL: Homepage, https://www.deepgreen.ai/en/platform
Project-URL: Documentation, https://eclipse.dev/aidge/
Project-URL: Repository, https://gitlab.eclipse.org/eclipse/aidge/aidge_export_cpp
Project-URL: Issues, https://gitlab.eclipse.org/eclipse/aidge/aidge_export_cpp/-/issues/
Project-URL: Changelog, https://gitlab.eclipse.org/eclipse/aidge/aidge_export_cpp/-/releases
Classifier: Development Status :: 2 - Pre-Alpha
Classifier: Intended Audience :: Developers
Classifier: Intended Audience :: Education
Classifier: Intended Audience :: Science/Research
Classifier: License :: OSI Approved :: Eclipse Public License 2.0 (EPL-2.0)
Classifier: Programming Language :: C++
Classifier: Programming Language :: Python
Classifier: Programming Language :: Python :: 3
Classifier: Programming Language :: Python :: 3.10
Classifier: Programming Language :: Python :: 3.11
Classifier: Programming Language :: Python :: 3.12
Classifier: Programming Language :: Python :: 3.13
Classifier: Programming Language :: Python :: 3 :: Only
Classifier: Topic :: Scientific/Engineering
Classifier: Topic :: Scientific/Engineering :: Artificial Intelligence
Classifier: Topic :: Software Development
Requires-Python: >=3.10
License-File: LICENSE
Requires-Dist: numpy>=1.20
Requires-Dist: Jinja2>=3.1.3
Provides-Extra: test
Requires-Dist: pytest; extra == "test"
Dynamic: license-file
